okapi_pkg/__init__.py
okapi_pkg/okapi.py
okapi_pkg/okapi_add_object.py
okapi_pkg/okapi_change_object.py
okapi_pkg/okapi_delete_object.py
okapi_pkg/okapi_get_objects.py
okapi_pkg/okapi_get_result.py
okapi_pkg/okapi_init.py
okapi_pkg/okapi_send_request.py
okapi_pkg/okapi_send_request_and_wait_for_result.py
okapi_pkg/okapi_wait_and_get_result.py
okapi_python_connector-2026.post1.dist-info/licenses/LICENSE
okapi_python_connector-2026.post1.dist-info/METADATA
okapi_python_connector-2026.post1.dist-info/WHEEL
okapi_python_connector-2026.post1.dist-info/top_level.txt
okapi_python_connector-2026.post1.dist-info/RECORD
