Metadata-Version: 2.4
Name: okapi-python-connector
Version: 2026.post1
Summary: Package to connect to OKAPI API
Home-page: https://github.com/OKAPIOrbits/OkapiPythonConnector
Author: OKAPI Orbits
Author-email: devops@okapiorbits.com
Classifier: Programming Language :: Python :: 3
Classifier: License :: OSI Approved :: MIT License
Classifier: Operating System :: OS Independent
License-File: LICENSE
Requires-Dist: requests
Dynamic: author
Dynamic: author-email
Dynamic: classifier
Dynamic: description
Dynamic: description-content-type
Dynamic: home-page
Dynamic: license-file
Dynamic: requires-dist
Dynamic: summary
